log.v
module log #(
    parameter DATA_SIZE = 32,
    parameter TAG_SIZE = 8,
    parameter MEM_DEPTH = 256  // Define the depth of the memory
) (
    input clk,
    input reset,
    input parity_error_in,
    input host_data_ready_in,
    input network_data_ready_in,
    input network_ack_in,
    input [DATA_SIZE-1:0] host_data_in,
    input [DATA_SIZE+TAG_SIZE-1:0] ndt_in,
    output reg [MEM_DEPTH-1:0][75:0] log_memory  // Memory to store log items
);

integer i = 0;  // Memory write pointer

always @(posedge clk) begin
    if (reset) begin
        for (i = 0; i < MEM_DEPTH; i = i + 1) begin
            log_memory[i] <= 76'd0;
        end
        i <= 0;
    end else if (i < MEM_DEPTH) begin
        // Condense all inputs into one item and store in memory
        log_memory[i] <= {parity_error_in, host_data_ready_in, network_data_ready_in, network_ack_in, host_data_in, ndt_in};
        i <= i + 1;  // Increment memory pointer
    end
end

endmodule

output_stage.v
module output_stage #(parameter data_size = 32, parameter tag_size = 8) (
    input clk,
    input reset,
    input[1:0] opcode_in,
    input soft_error_in,
    input[(data_size-1):0] tx_data_in,
    input[(tag_size-1):0] tx_tag_in,
    input[(data_size+tag_size-1):0] tx_data_plus_tag_in,
    input tag_match_in,
    input[(data_size-1):0] rx_data_in,
    input[(data_size+tag_size-1):0] ndt_in,
    output reg parity_error_out,
    output reg host_data_ready_out,
    output reg network_data_ready_out,
    output reg network_ack_out,
    output reg[(data_size-1):0] host_data_out,
    output reg[(data_size+tag_size-1):0] ndt_out
    );
    
    localparam OP_RXA = 2'b10;
    localparam OP_TXE = 2'b01;
    
    // AND gates ordered from top to bottom in datapath diagram
    assign and_gate_1 = (opcode_in == OP_RXA);
    assign and_gate_2 = (opcode_in == OP_TXE);
    assign and_gate_3 = (~parity_error_out & and_gate_2);
    assign and_gate_4 = (tag_match_in & and_gate_1);
    
    // OR gates ordered from top to bottom in datapath diagram
    assign or_gate_1 = (parity_error_out | and_gate_4);
    assign or_gate_2 = (and_gate_3 | and_gate_4);
    
    // MUX's ordered from top to bottom
    wire [(data_size-1):0] mux_1;
    wire [(data_size+tag_size-1):0] mux_2;
    assign mux_1 = parity_error_out ? tx_data_in : rx_data_in;
    assign mux_2 = (opcode_in == OP_TXE) ? tx_data_plus_tag_in : ndt_in;
    
    always @(negedge clk) begin
        if (reset) begin
            parity_error_out <= 0;
            host_data_ready_out <= 0;
            network_data_ready_out <= 0;
            network_ack_out <= 0;
            host_data_out <= 0;
            ndt_out <= 0;
        end else begin
            parity_error_out <= soft_error_in;
            host_data_ready_out <= or_gate_1;
            network_data_ready_out <= or_gate_2;
            network_ack_out <= and_gate_4; 
            host_data_out <= mux_1;
            ndt_out <= mux_2;
        end
    end
    
endmodule

stage_3.v
module stage_3 #(parameter data_size = 32, parameter tag_size = 8) (
    // CLK/RST Signals
    input clk,
    input reset,

    // Opcodes (2 bits)
    input[1:0] opcode_in,
    output reg[1:0] opcode_out,

    // Soft Error Flag
    input soft_error_in,
    output reg soft_error_out,

    // TX Data and its computed tag (data_size bits, tag_size bits)
    input[(data_size-1):0] tx_data_in,
    input[(tag_size-1):0] tx_tag_in,
    output reg[(data_size-1):0] tx_data_out,
    output reg[(tag_size-1):0] tx_tag_out,

    // RX Tag Match Flag
    input tag_match_in,
    output reg tag_match_out,

    // Network Data Plus Tag (NDT) (data_size+tag_size bits)
    input[(data_size+tag_size-1):0] ndt_in,
    output reg[(data_size+tag_size-1):0] ndt_out,

    // RX/TX Signals (More to come)
    output[(data_size-1):0] rx_data_out,
    output[(data_size+tag_size-1):0] tx_data_plus_tag
);
    // Data from the network
    // Note that the tag is the last (tag_size) bits of NDT
    assign rx_data = ndt_out[(data_size+tag_size-1):tag_size];

    // Data from the host with its computed tag to be sent over the network if there is no soft error
    assign tx_data_plus_tag = {tx_data_out,tx_tag_out};

    // Reset/Update outputs on positive edge of clock
    always @(posedge clk) begin
        if (reset) begin
            opcode_out <= 0;
            soft_error_out <= 0;
            tx_data_out <= 0;
            tx_tag_out <= 0;
            tag_match_out <= 0;
            ndt_out <= 0;
        end else begin
            opcode_out <= opcode_in;
            soft_error_out <= soft_error_in;
            tx_data_out <= tx_data_in;
            tx_tag_out <= tx_tag_in;
            tag_match_out <= tag_match_in;
            ndt_out <= ndt_in;
        end
    end

endmodule

tag_generation.v
module tag_generation #(
    parameter DATA_SIZE = 32,  // Parameter for the size of data
    parameter TAG_SIZE = 8,    // Parameter for the size of the tag
    parameter KEY_SIZE = 16    // Parameter for the size of the secret key
) (
    input wire clk,                  // Clock signal
    input wire reset,                // Reset signal
    input wire [DATA_SIZE-1:0] data, // Data input
    output reg [TAG_SIZE-1:0] tag    // Tag output
);

// Assume SECRET_KEY is a parameter passed to the module or hardcoded within it.
parameter [KEY_SIZE-1:0] SECRET_KEY = 16'hDEAD; // Secret key

// Internal signal for the combined tag result, declared as a reg for use within always blocks
reg [TAG_SIZE-1:0] xor_result;

// Function for the Rotate Left Shift (RLS) operation
function [TAG_SIZE-1:0] RLS_FUNCTION;
    input [TAG_SIZE-1:0] block;
    input integer bits;
    begin
        RLS_FUNCTION = (block << bits) | (block >> (TAG_SIZE - bits));
    end
endfunction

// Generate block flip (BF) and rotate left shift (RLS) for each block
genvar i;
wire [TAG_SIZE-1:0] block_flipped [0:DATA_SIZE/TAG_SIZE-1];
wire [TAG_SIZE-1:0] rotated_blocks [0:DATA_SIZE/TAG_SIZE-1];
generate
    for (i = 0; i < DATA_SIZE/TAG_SIZE; i = i + 1) begin : gen_bf_rls
        // Calculate the block flip for each segment
        assign block_flipped[i] = (SECRET_KEY[i] ? ~data[i*TAG_SIZE+:TAG_SIZE] : data[i*TAG_SIZE+:TAG_SIZE]);
        // Calculate the RLS for each flipped block
        assign rotated_blocks[i] = RLS_FUNCTION(block_flipped[i], SECRET_KEY[2*i+:2]);
    end
endgenerate

// Compute the tag by XOR'ing all the rotated blocks
integer j;
always @(posedge clk or posedge reset) begin
    if (reset) begin
        xor_result <= 0;
    end else begin
        xor_result <= rotated_blocks[0];
        for (j = 1; j < DATA_SIZE/TAG_SIZE; j = j + 1) begin
            xor_result <= xor_result ^ rotated_blocks[j];
        end
    end
end

// Output the final tag value
always @(posedge clk or posedge reset) begin
    if (reset) begin
        tag <= 0;
    end else begin
        tag <= xor_result;
    end
end

endmodule

stage_2.v
module stage_2 #(parameter data_size = 32, parameter tag_size = 8) (
    // CLK/RST Signals
    input clk,
    input reset,

    // Opcodes (2 bits)
    input[1:0] opcode_in,
    output reg[1:0] opcode_out,

    // Soft Error Flag
    input soft_error_in,
    output reg soft_error_out,

    // Data Plus Parity (DPP) (data_size+1 bits)
    input[(data_size):0] dpp_in,
    output reg[(data_size):0] dpp_out,

    // Network Data Plus Tag (NDT) (data_size+tag_size bits)
    input[(data_size+tag_size-1):0] ndt_in,
    output reg[(data_size+tag_size-1):0] ndt_out,

    // RX/TX Signals for MUX
    output[(data_size-1):0] rx_data, 
    output[(data_size-1):0] tx_data,
    output[(tag_size-1):0] rx_tag
);

    // Data from the host that has been parity checked (DPP)
    assign tx_data = dpp_out[(data_size):1];

    // From the network to be tag checked (NDT)
    // Note that the tag is the last (tag_size) bits of NDT
    assign rx_data = ndt_out[(data_size+tag_size-1):tag_size];
    assign rx_tag = ndt_out[(tag_size-1):0];

    // Reset/Update outputs on positive edge of clock
    always @(posedge clk) begin
        if (reset) begin
            opcode_out <= 0;
            soft_error_out <= 0;
            dpp_out <= 0;
            ndt_out <= 0;
        end else begin
            opcode_out <= opcode_in;
            soft_error_out <= soft_error_in;
            dpp_out <= dpp_in;
            ndt_out <= ndt_in;
        end
    end

endmodule

soft_error_detection.v
module soft_error_detection #(parameter data_size = 32) (
    input clk,
    input reset,
    input[data_size-1:0] data,
    input parity_bit,
    output reg soft_error_flag
    );
    
    // Calculate the parity of the input data (even parity) by using reduction XOR operation
    wire calculated_parity = ^data;
    
    // Check if the calulcated parity matches the recevied parity bit
    always @(posedge clk) begin
        if (reset) begin
            soft_error_flag <= 1'b0;
        end else begin    
            if (calculated_parity == parity_bit) begin
                // No soft error detected
                soft_error_flag <= 1'b0;
            end else begin
                // Soft error detected
                soft_error_flag <= 1'b1;
            end
        end   
    end
endmodule

stage_1.v
module stage_1 #(parameter data_size = 32, parameter tag_size = 8) (
    // CLK/RST Signals
    input clk,
    input reset,

    // Opcodes (2 bits)
    input[1:0] opcode_in,
    output reg[1:0] opcode_out,

    // Data Plus Parity (DPP) (data_size+1 bits)
    input[(data_size):0] dpp_in,
    output reg[(data_size):0] dpp_out,

    // Network Data Plus Tag (NDT) (data_size+tag_size bits)
    input[(data_size+tag_size-1):0] ndt_in,
    output reg[(data_size+tag_size-1):0] ndt_out
);

    // Reset/Update outputs on positive edge of clock
    always @(posedge clk) begin
        if (reset) begin
            opcode_out <= 0;
            dpp_out <= 0;
            ndt_out <= 0;
        end else begin
            opcode_out <= opcode_in;
            dpp_out <= dpp_in;
            ndt_out <= ndt_in;
        end
    end

endmodule

control_unit.v
module control_unit(
    input clk,
    input reset,
    input dpp_ready_in,
    input nd_ready_in,
    input na_in,
    output reg[1:0] opcode_out
    );
    
    localparam OP_NOP = 2'b00;
    localparam OP_TXE = 2'b01;
    localparam OP_RXA = 2'b10;
    localparam OP_LOG = 2'b11;
    
    always @(posedge clk) begin 
        if (reset) begin
            opcode_out <= OP_NOP;
        end else begin
            
            // priority system which prioritizes receving
            if (nd_ready_in) begin
                opcode_out <= OP_RXA;
            end else if (dpp_ready_in) begin
                opcode_out <= OP_TXE;
            end else if (na_in) begin
                opcode_out <= OP_LOG;
            end else begin
                opcode_out = OP_NOP;
            end

            // OLD version, non-priority system
            //case ({dpp_ready_in, nd_ready_in, na_in}) 
                // Dylan: I think we should change this to a priority system. What happens if we get a signal from the network and the host at the same time?
                //default: opcode_out <= OP_NOP;
                //3'b100: opcode_out <= OP_TXE;
                //3'b010: opcode_out <= OP_RXA;
                //3'b001: opcode_out <= OP_LOG;
             //endcase 
        end        
    end
    
endmodule

ASP.v
module ASP #(parameter data_size = 32, parameter tag_size = 8, parameter mem_depth = 256) (
    // Control Inputs
    input clk,
    input reset,

    // Data from Host & controls
    input data_parity_ready_in,
    input[(data_size):0] data_parity_in,

    // Data from Network & controls
    input network_data_ready_in,
    input network_ACK_in,
    input[(data_size+tag_size-1):0] network_data_tag_in,

    // Data to Host & controls
    output parity_error_out,
    output host_data_ready_out,
    output[(data_size-1):0] host_data_out,

    // Data to Network & controls
    output network_data_ready_out,
    output network_ACK_out,
    output[(data_size+tag_size-1):0] network_data_tag_out
);

    // ======== Instruction Decode ===========
    
    // Internal Signals
    wire[1:0] ID_opcode;

    // Control Unit
    control_unit control_unit_inst(clk, reset, data_parity_ready_in, network_data_ready_in, network_ACK_in, ID_opcode);

    // == ID/L1 Pipeline Register ==
    stage_1 #(.data_size(data_size), .tag_size(tag_size)) id_l1_pipeline_reg(clk, reset, ID_opcode, layer1_opcode, data_parity_in, layer1_dpp, network_data_tag_in, layer1_ndt);

    // =============== Layer 1 ===============

    // Pipeline Register Signals
    wire[1:0] layer1_opcode;
    wire[(data_size):0] layer1_dpp;
    wire[(data_size+tag_size-1):0] layer1_ndt;
    wire layer1_error_detected;

    // Soft Error Detector
    soft_error_detection #(.data_size(data_size)) SED_inst(clk, reset, layer1_dpp[data_size:1], layer1_dpp[0], layer1_error_detected);
    
    // == L1/L2 Pipeline Register ==
    stage_2 #(.data_size(data_size), .tag_size(tag_size)) l1_l2_pipeline_reg(clk, reset, layer1_opcode, layer2_opcode, layer1_error_detected, layer2_error_detected, layer1_dpp, layer2_dpp, layer1_ndt, layer2_ndt, layer2_rx_data, layer2_tx_data, layer2_rx_tag);

    // =============== Layer 2 ===============

    // Pipeline Register Signals
    wire[1:0] layer2_opcode;
    wire[(data_size):0] layer2_dpp;
    wire[(data_size-1):0] layer2_tx_data;
    wire[(data_size-1):0] layer2_rx_data;
    wire[(tag_size-1):0] layer2_rx_tag;
    wire[(tag_size-1):0] layer2_computed_tag;
    wire layer2_tag_match;
    wire[(data_size+tag_size-1):0] layer2_ndt;
    wire layer2_error_detected;

    // Internal Signals
    wire[(data_size-1):0] layer2_TGEN_data_in;
    wire[15:0] secret_key;

    // Multiplexer
    // Will assign layer2_TGEN_data_in to either layer2_tx_data or layer2_rx_data depending on the opcode.

    // Tag Generator
    tag_generation #(.DATA_SIZE(data_size), .TAG_SIZE(tag_size)) tag_gen_inst(clk, reset, layer2_TGEN_data_in, layer2_computed_tag);

    // Comparator
    assign layer2_tag_match = (layer2_computed_tag == layer2_rx_tag);

    // == L2/OL Pipeline Register ==
    stage_3 #(.data_size(data_size), .tag_size(tag_size)) l2_ol_pipeline_reg(clk, reset, layer2_opcode, OL_opcode, layer2_error_detected, OL_error_detected, layer2_tx_data, layer2_computed_tag, OL_tx_data, OL_tx_tag, layer2_tag_match, OL_tag_match, layer2_ndt, OL_ndt, OL_rx_data, OL_tx_data_tagged);

    // ============ Output Layer =============

    // Pipeline Register Signals
    wire[1:0] OL_opcode;
    wire[(data_size-1):0] OL_tx_data;
    wire[(data_size+tag_size-1):0] OL_tx_data_tagged;
    wire[(tag_size-1):0] OL_tx_tag;
    wire OL_tag_match;
    wire[(data_size-1):0] OL_rx_data;
    wire[(data_size+tag_size-1):0] OL_ndt;
    wire OL_error_detected;

    // Output Stage Module
    output_stage output_stage_inst(clk, reset, OL_opcode, OL_error_detected, OL_tx_data, OL_tx_tag, OL_tx_data_tagged, OL_tag_match, OL_rx_data, OL_ndt, parity_error_out, host_data_ready_out, network_data_ready_out, network_ACK_out, host_data_out, network_data_tag_out);

    // Logging Module
    wire[mem_depth-1:0][75:0] log_memory;
    log #(.DATA_SIZE(data_size), .TAG_SIZE(tag_size), .MEM_DEPTH(mem_depth)) log_inst(clk, reset, OL_error_detected, host_data_ready_out, network_data_ready_out, network_ACK_out, OL_tx_data, OL_ndt, log_memory);
endmodule

ASP_TXE_tb.v
`timescale 1ns/1ns

module ASP_TXE_tb();
    parameter DATA_SIZE = 32;
    parameter TAG_SIZE = 8;

    reg clk;
    reg reset;

    reg data_parity_ready_in;
    reg[(DATA_SIZE):0] data_parity_in;

    reg network_data_ready_in;
    reg network_ACK_in;
    reg[(DATA_SIZE+TAG_SIZE-1):0] network_data_tag_in;

    wire parity_error_out;
    wire host_data_ready_out;
    wire[(DATA_SIZE-1):0] host_data_out;

    wire network_data_ready_out;
    wire network_ACK_out;
    wire[(DATA_SIZE+TAG_SIZE-1):0] network_data_tag_out;

    ASP #(.data_size(DATA_SIZE), .tag_size(TAG_SIZE)) ASP_inst(clk, reset, data_parity_ready_in, data_parity_in, network_data_ready_in, network_ACK_in, network_data_tag_in, parity_error_out, host_data_ready_out, host_data_out, network_data_ready_out, network_ACK_out, network_data_tag_out);

    always #10 clk = ~clk;

    initial begin
        $dumpfile("dumpfiles/ASP_TXE_tb.vcd");
        $dumpvars(0,ASP_TXE_tb);

        // Initialization
        clk = 0;
        reset = 1;
        data_parity_ready_in = 0;
        data_parity_in = 0;
        network_data_ready_in = 0;
        network_ACK_in = 0;
        network_data_tag_in = 0;
        #10
        #10
        reset = 0;

        // Test case 1: Data transmission with no soft error
        data_parity_ready_in = 1;
        network_data_ready_in = 0;
        network_ACK_in = 0;
        data_parity_in = 33'b101001011010010110100101101001010; // data plus correct parity bit (0)
        network_data_tag_in = 0;
        #20;

        // Test case 2: Data transmission with soft error
        data_parity_ready_in = 1;
        network_data_ready_in = 0;
        network_ACK_in = 0;
        data_parity_in = 33'b101001011010010110100101101001011; // data plus incorrect parity bit (1)
        network_data_tag_in = 0;
        #20;
        #20;
        #20;
        #20;
        #20;
        #20;
        
        
        $finish;
	end

endmodule

dumpfiles/ASP_TXE_tb.vcd
$date
	Tue Apr 16 17:17:09 2024
$end
$version
	Icarus Verilog
$end
$timescale
	1ns
$end
$scope module ASP_TXE_tb $end
$var wire 1 ! parity_error_out $end
$var wire 40 " network_data_tag_out [39:0] $end
$var wire 1 # network_data_ready_out $end
$var wire 1 $ network_ACK_out $end
$var wire 1 % host_data_ready_out $end
$var wire 32 & host_data_out [31:0] $end
$var reg 1 ' clk $end
$var reg 33 ( data_parity_in [32:0] $end
$var reg 1 ) data_parity_ready_in $end
$var reg 1 * network_ACK_in $end
$var reg 1 + network_data_ready_in $end
$var reg 40 , network_data_tag_in [39:0] $end
$var reg 1 - reset $end
$scope module ASP_inst $end
$var wire 1 ' clk $end
$var wire 33 . data_parity_in [32:0] $end
$var wire 1 ) data_parity_ready_in $end
$var wire 32 / layer2_TGEN_data_in [31:0] $end
$var wire 1 * network_ACK_in $end
$var wire 1 + network_data_ready_in $end
$var wire 40 0 network_data_tag_in [39:0] $end
$var wire 1 - reset $end
$var wire 1 ! parity_error_out $end
$var wire 40 1 network_data_tag_out [39:0] $end
$var wire 1 # network_data_ready_out $end
$var wire 1 $ network_ACK_out $end
$var wire 19456 2 log_memory [19455:0] $end
$var wire 32 3 layer2_tx_data [31:0] $end
$var wire 1 4 layer2_tag_match $end
$var wire 8 5 layer2_rx_tag [7:0] $end
$var wire 32 6 layer2_rx_data [31:0] $end
$var wire 2 7 layer2_opcode [1:0] $end
$var wire 40 8 layer2_ndt [39:0] $end
$var wire 1 9 layer2_error_detected $end
$var wire 33 : layer2_dpp [32:0] $end
$var wire 8 ; layer2_computed_tag [7:0] $end
$var wire 2 < layer1_opcode [1:0] $end
$var wire 40 = layer1_ndt [39:0] $end
$var wire 1 > layer1_error_detected $end
$var wire 33 ? layer1_dpp [32:0] $end
$var wire 1 % host_data_ready_out $end
$var wire 32 @ host_data_out [31:0] $end
$var wire 8 A OL_tx_tag [7:0] $end
$var wire 40 B OL_tx_data_tagged [39:0] $end
$var wire 32 C OL_tx_data [31:0] $end
$var wire 1 D OL_tag_match $end
$var wire 32 E OL_rx_data [31:0] $end
$var wire 2 F OL_opcode [1:0] $end
$var wire 40 G OL_ndt [39:0] $end
$var wire 1 H OL_error_detected $end
$var wire 2 I ID_opcode [1:0] $end
$scope module SED_inst $end
$var wire 1 ' clk $end
$var wire 32 J data [31:0] $end
$var wire 1 K parity_bit $end
$var wire 1 - reset $end
$var wire 1 L calculated_parity $end
$var reg 1 > soft_error_flag $end
$upscope $end
$scope module control_unit_inst $end
$var wire 1 ' clk $end
$var wire 1 ) dpp_ready_in $end
$var wire 1 * na_in $end
$var wire 1 + nd_ready_in $end
$var wire 1 - reset $end
$var reg 2 M opcode_out [1:0] $end
$upscope $end
$scope module id_l1_pipeline_reg $end
$var wire 1 ' clk $end
$var wire 33 N dpp_in [32:0] $end
$var wire 40 O ndt_in [39:0] $end
$var wire 2 P opcode_in [1:0] $end
$var wire 1 - reset $end
$var reg 33 Q dpp_out [32:0] $end
$var reg 40 R ndt_out [39:0] $end
$var reg 2 S opcode_out [1:0] $end
$upscope $end
$scope module l1_l2_pipeline_reg $end
$var wire 1 ' clk $end
$var wire 33 T dpp_in [32:0] $end
$var wire 40 U ndt_in [39:0] $end
$var wire 2 V opcode_in [1:0] $end
$var wire 1 - reset $end
$var wire 1 > soft_error_in $end
$var wire 32 W tx_data [31:0] $end
$var wire 8 X rx_tag [7:0] $end
$var wire 32 Y rx_data [31:0] $end
$var reg 33 Z dpp_out [32:0] $end
$var reg 40 [ ndt_out [39:0] $end
$var reg 2 \ opcode_out [1:0] $end
$var reg 1 9 soft_error_out $end
$upscope $end
$scope module l2_ol_pipeline_reg $end
$var wire 1 ' clk $end
$var wire 40 ] ndt_in [39:0] $end
$var wire 2 ^ opcode_in [1:0] $end
$var wire 1 - reset $end
$var wire 1 9 soft_error_in $end
$var wire 1 4 tag_match_in $end
$var wire 32 _ tx_data_in [31:0] $end
$var wire 8 ` tx_tag_in [7:0] $end
$var wire 40 a tx_data_plus_tag [39:0] $end
$var wire 32 b rx_data_out [31:0] $end
$var reg 40 c ndt_out [39:0] $end
$var reg 2 d opcode_out [1:0] $end
$var reg 1 H soft_error_out $end
$var reg 1 D tag_match_out $end
$var reg 32 e tx_data_out [31:0] $end
$var reg 8 f tx_tag_out [7:0] $end
$upscope $end
$scope module log_inst $end
$var wire 1 ' clk $end
$var wire 32 g host_data_in [31:0] $end
$var wire 40 h ndt_in [39:0] $end
$var wire 1 H parity_error_in $end
$var wire 1 - reset $end
$var wire 1 # network_data_ready_in $end
$var wire 1 $ network_ack_in $end
$var wire 1 % host_data_ready_in $end
$var reg 19456 i log_memory [19455:0] $end
$var integer 32 j i [31:0] $end
$upscope $end
$scope module output_stage_inst $end
$var wire 1 k and_gate_3 $end
$var wire 1 l and_gate_4 $end
$var wire 1 ' clk $end
$var wire 40 m ndt_in [39:0] $end
$var wire 2 n opcode_in [1:0] $end
$var wire 1 o or_gate_1 $end
$var wire 1 p or_gate_2 $end
$var wire 1 - reset $end
$var wire 32 q rx_data_in [31:0] $end
$var wire 1 H soft_error_in $end
$var wire 1 D tag_match_in $end
$var wire 32 r tx_data_in [31:0] $end
$var wire 40 s tx_data_plus_tag_in [39:0] $end
$var wire 8 t tx_tag_in [7:0] $end
$var wire 40 u mux_2 [39:0] $end
$var wire 32 v mux_1 [31:0] $end
$var wire 1 w and_gate_2 $end
$var wire 1 x and_gate_1 $end
$var reg 32 y host_data_out [31:0] $end
$var reg 1 % host_data_ready_out $end
$var reg 40 z ndt_out [39:0] $end
$var reg 1 $ network_ack_out $end
$var reg 1 # network_data_ready_out $end
$var reg 1 ! parity_error_out $end
$upscope $end
$scope module tag_gen_inst $end
$var wire 1 ' clk $end
$var wire 32 { data [31:0] $end
$var wire 1 - reset $end
$var reg 8 | tag [7:0] $end
$var reg 8 } xor_result [7:0] $end
$var integer 32 ~ j [31:0] $end
$scope function RLS_FUNCTION $end
$var reg 8 !" block [7:0] $end
$var integer 32 "" bits [31:0] $end
$upscope $end
$scope begin gen_bf_rls[0] $end
$upscope $end
$scope begin gen_bf_rls[1] $end
$upscope $end
$scope begin gen_bf_rls[2] $end
$upscope $end
$scope begin gen_bf_rls[3] $end
$upscope $end
$upscope $end
$upscope $end
$upscope $end
$enddefinitions $end
#0
$dumpvars
b10 ""
bx !"
bx ~
b0 }
b0 |
bz {
b0 z
b0 y
xx
xw
bx v
bx u
bx t
bx s
bx r
bx q
xp
xo
bx n
bx m
xl
xk
b0 j
bx i
bx h
bx g
bx f
bx e
bx d
bx c
bx b
bx a
b0 `
bx _
bx ^
bx ]
bx \
bx [
bx Z
bx Y
bx X
bx W
bx V
bx U
bx T
bx S
bx R
bx Q
bx P
b0 O
b0 N
bx M
xL
xK
bx J
bx I
xH
bx G
bx F
bx E
xD
bx C
bx B
bx A
b0 @
bx ?
x>
bx =
bx <
b0 ;
bx :
x9
bx 8
bx 7
bx 6
bx 5
x4
bx 3
bx 2
b0 1
b0 0
bz /
b0 .
1-
b0 ,
0+
0*
0)
b0 (
0'
b0 &
0%
0$
0#
b0 "
0!
$end
#10
b0 v
0o
0p
0K
0L
b0 J
b0 6
b0 Y
14
b0 5
b0 X
b0 3
b0 W
b0 _
b0 E
b0 b
b0 q
0l
0k
b0 u
b0 I
b0 M
b0 P
b0 =
b0 R
b0 U
b0 ?
b0 Q
b0 T
b0 <
b0 S
b0 V
0>
b0 8
b0 [
b0 ]
b0 :
b0 Z
09
b0 7
b0 \
b0 ^
b0 G
b0 c
b0 h
b0 m
0D
b0 A
b0 f
b0 t
b0 B
b0 a
b0 s
b0 C
b0 e
b0 g
b0 r
0H
0x
0w
b0 F
b0 d
b0 n
b0 2
b0 i
b0 j
1'
#20
b101001011010010110100101101001010 (
b101001011010010110100101101001010 .
b101001011010010110100101101001010 N
1)
0-
0'
#30
b10100101101001011010010110100101 J
b1 j
1D
b101001011010010110100101101001010 ?
b101001011010010110100101101001010 Q
b101001011010010110100101101001010 T
b1 I
b1 M
b1 P
bx }
b100 ~
1'
#40
0'
b101001011010010110100101101001011 (
b101001011010010110100101101001011 .
b101001011010010110100101101001011 N
#50
1K
b10100101101001011010010110100101 3
b10100101101001011010010110100101 W
b10100101101001011010010110100101 _
b101001011010010110100101101001011 ?
b101001011010010110100101101001011 Q
b101001011010010110100101101001011 T
b1 <
b1 S
b1 V
b101001011010010110100101101001010 :
b101001011010010110100101101001010 Z
b10 j
x4
bx ;
bx `
bx |
b100 ~
1'
#60
0'
#70
b11 j
xD
bx A
bx f
bx t
b10100101101001011010010110100101xxxxxxxx B
b10100101101001011010010110100101xxxxxxxx a
b10100101101001011010010110100101xxxxxxxx s
b10100101101001011010010110100101 C
b10100101101001011010010110100101 e
b10100101101001011010010110100101 g
b10100101101001011010010110100101 r
b101001011010010110100101101001011 :
b101001011010010110100101101001011 Z
b1 7
b1 \
b1 ^
1>
b100 ~
1'
#80
0'
#90
1p
1k
b10100101101001011010010110100101xxxxxxxx u
19
1w
b1 F
b1 d
b1 n
b100 j
b101001011010010110100101101001010000000000000000000000000000000000000000000000000000000000000000000000000000000000000000000000000000000000000000000000000000000000000000000000000000000000000000000000000000000000000000000000000000000000000000000000000000000000000000000000000000000000000000000000000000 2
b101001011010010110100101101001010000000000000000000000000000000000000000000000000000000000000000000000000000000000000000000000000000000000000000000000000000000000000000000000000000000000000000000000000000000000000000000000000000000000000000000000000000000000000000000000000000000000000000000000000000 i
b100 ~
1'
#100
b10100101101001011010010110100101xxxxxxxx "
b10100101101001011010010110100101xxxxxxxx 1
b10100101101001011010010110100101xxxxxxxx z
1#
0'
#110
b101 j
b101010010110100101101001011010010100000000000000000000000000000000000000000000101001011010010110100101101001010000000000000000000000000000000000000000000000000000000000000000000000000000000000000000000000000000000000000000000000000000000000000000000000000000000000000000000000000000000000000000000000000000000000000000000000000000000000000000000000000000000000000000000000000000 2
b101010010110100101101001011010010100000000000000000000000000000000000000000000101001011010010110100101101001010000000000000000000000000000000000000000000000000000000000000000000000000000000000000000000000000000000000000000000000000000000000000000000000000000000000000000000000000000000000000000000000000000000000000000000000000000000000000000000000000000000000000000000000000000 i
1H
b100 ~
1'
#120
0p
0k
b10100101101001011010010110100101 v
1o
1!
0'
#130
b110 j
b101010100101101001011010010110100101000000000000000000000000000000000000000000101010010110100101101001011010010100000000000000000000000000000000000000000000101001011010010110100101101001010000000000000000000000000000000000000000000000000000000000000000000000000000000000000000000000000000000000000000000000000000000000000000000000000000000000000000000000000000000000000000000000000000000000000000000000000000000000000000000000000000000000000000000000000000 2
b101010100101101001011010010110100101000000000000000000000000000000000000000000101010010110100101101001011010010100000000000000000000000000000000000000000000101001011010010110100101101001010000000000000000000000000000000000000000000000000000000000000000000000000000000000000000000000000000000000000000000000000000000000000000000000000000000000000000000000000000000000000000000000000000000000000000000000000000000000000000000000000000000000000000000000000000 i
b100 ~
1'
#140
b10100101101001011010010110100101 &
b10100101101001011010010110100101 @
b10100101101001011010010110100101 y
0#
1%
0'
#150
b111 j
b1100101001011010010110100101101001010000000000000000000000000000000000000000101010100101101001011010010110100101000000000000000000000000000000000000000000101010010110100101101001011010010100000000000000000000000000000000000000000000101001011010010110100101101001010000000000000000000000000000000000000000000000000000000000000000000000000000000000000000000000000000000000000000000000000000000000000000000000000000000000000000000000000000000000000000000000000000000000000000000000000000000000000000000000000000000000000000000000000000 2
b1100101001011010010110100101101001010000000000000000000000000000000000000000101010100101101001011010010110100101000000000000000000000000000000000000000000101010010110100101101001011010010100000000000000000000000000000000000000000000101001011010010110100101101001010000000000000000000000000000000000000000000000000000000000000000000000000000000000000000000000000000000000000000000000000000000000000000000000000000000000000000000000000000000000000000000000000000000000000000000000000000000000000000000000000000000000000000000000000000 i
b100 ~
1'
